{"frames": [

{
	"filename": "Symbol 4 instance 10000",
	"frame": {"x":0,"y":0,"w":77,"h":169},
	"rotated": false,
	"trimmed": false,
	"spriteSourceSize": {"x":0,"y":0,"w":77,"h":169},
	"sourceSize": {"w":77,"h":169}
}
,{
	"filename": "Symbol 4 instance 10001",
	"frame": {"x":77,"y":0,"w":77,"h":169},
	"rotated": false,
	"trimmed": false,
	"spriteSourceSize": {"x":0,"y":0,"w":77,"h":169},
	"sourceSize": {"w":77,"h":169}
}],
"meta": {
	"app": "Adobe Animate",
	"version": "18.0.0.107",
	"image": "200ml q.png",
	"format": "RGBA8888",
	"size": {"w":256,"h":256},
	"scale": "1"
}
}
